anna/LICENSE
anna/VERSION
anna/__init__.py
anna/adaptors.py
anna/configuration.py
anna/datatypes.py
anna/dependencies.py
anna/exceptions.py
anna/input.py
anna/parameters.py
anna/sweeps.py
anna/utils.py
anna/frontends/__init__.py
anna/frontends/qt/__init__.py
anna/frontends/qt/dialogs.py
anna/frontends/qt/forms.py
anna/frontends/qt/parameters.py
anna/frontends/qt/pyqt45.py
anna/frontends/qt/sweeps.py
anna/frontends/qt/utils.py
anna/frontends/qt/views.py
anna/frontends/qt/widgets.py
anna/frontends/qt/icons/info.png
anna/frontends/qt/icons/parameter_info.png
anna/unittests/__init__.py
anna/unittests/adaptors.py
anna/unittests/configuration.py
anna/unittests/parameters.py
anna-0.5.2.dist-info/LICENSE
anna-0.5.2.dist-info/METADATA
anna-0.5.2.dist-info/WHEEL
anna-0.5.2.dist-info/top_level.txt
anna-0.5.2.dist-info/RECORD
