Metadata-Version: 2.1
Name: anna
Version: 0.5.2
Summary: A Neat configuratioN Auxiliary
Home-page: https://gitlab.com/Dominik1123/Anna
Author: Dominik Vilsmeier
Author-email: dominik.vilsmeier1123@gmail.com
License: BSD-3-Clause
Keywords: configuration framework
Platform: UNKNOWN
Classifier: Development Status :: 4 - Beta
Classifier: License :: OSI Approved :: BSD License
Classifier: Programming Language :: Python :: 2.7
Classifier: Programming Language :: Python :: 3.5
Classifier: Programming Language :: Python :: 3.6
Classifier: Programming Language :: Python :: 3.7
Classifier: Programming Language :: Python :: 3.8
Classifier: Programming Language :: Python :: 3.9
Classifier: Topic :: Software Development
Requires-Dist: docutils
Requires-Dist: numpy
Requires-Dist: scipy
Requires-Dist: six
